cledatatoolkit/__init__.py
cledatatoolkit/ago_helpers.py
cledatatoolkit/census.py
cledatatoolkit/property.py
cledatatoolkit/spatial.py
cle_data_toolkit-1.0.2.dist-info/LICENSE
cle_data_toolkit-1.0.2.dist-info/METADATA
cle_data_toolkit-1.0.2.dist-info/WHEEL
cle_data_toolkit-1.0.2.dist-info/top_level.txt
cle_data_toolkit-1.0.2.dist-info/RECORD
