Metadata-Version: 2.1
Name: cle-data-toolkit
Version: 1.0.2
Summary: A project developed by the City of Cleveland Office of Urban Analytics and Innovation, built to simplify civic data processing for the public.
Author-email: Shelley Murphy <smurphy3@clevelandohio.gov>, Sam Martinez <smartinez2@clevelandohio.gov>, Dro Sohrabian <dsohrabian@clevelandohio.gov>
Project-URL: Homepage, https://github.com/City-of-Cleveland/cledatatoolkit/
Project-URL: Issues, https://github.com/City-of-Cleveland/cledatatoolkit/issues
Requires-Python: >=3.9
License-File: LICENSE
Requires-Dist: geopandas
Requires-Dist: pandas
Requires-Dist: requests ==2.31.0
Requires-Dist: ipykernel
Requires-Dist: arcgis ==2.2.0
Requires-Dist: libpysal
Requires-Dist: dask[dataframe]
